Metadata-Version: 1.0
Name: requestsModel
Version: 2.1.1
Summary: requests_Model
Home-page: UNKNOWN
Author: donglidunyin
Author-email: donglidunyin@163.com
License: UNKNOWN
Platform: UNKNOWN
